prime_sdk/__init__.py
prime_sdk/base_response.py
prime_sdk/client.py
prime_sdk/client_services.py
prime_sdk/credentials.py
prime_sdk/enums.py
prime_sdk/model.py
prime_sdk/utils.py
prime_sdk/services/__init__.py
prime_sdk/services/activities/__init__.py
prime_sdk/services/activities/get_activity.py
prime_sdk/services/activities/get_entity_activity.py
prime_sdk/services/activities/list_activities.py
prime_sdk/services/activities/list_entity_activities.py
prime_sdk/services/activities/service.py
prime_sdk/services/address_book/__init__.py
prime_sdk/services/address_book/create_address_book_entry.py
prime_sdk/services/address_book/get_address_book.py
prime_sdk/services/address_book/service.py
prime_sdk/services/allocations/__init__.py
prime_sdk/services/allocations/create_portfolio_allocations.py
prime_sdk/services/allocations/create_portfolio_net_allocations.py
prime_sdk/services/allocations/get_allocation_by_id.py
prime_sdk/services/allocations/get_net_allocations_by_netting_id.py
prime_sdk/services/allocations/list_portfolio_allocations.py
prime_sdk/services/allocations/service.py
prime_sdk/services/assets/__init__.py
prime_sdk/services/assets/list_assets.py
prime_sdk/services/assets/service.py
prime_sdk/services/balances/__init__.py
prime_sdk/services/balances/get_wallet_balance.py
prime_sdk/services/balances/list_entity_balances.py
prime_sdk/services/balances/list_portfolio_balances.py
prime_sdk/services/balances/list_web3_wallet_balances.py
prime_sdk/services/balances/service.py
prime_sdk/services/commission/__init__.py
prime_sdk/services/commission/get_portfolio_commission.py
prime_sdk/services/commission/service.py
prime_sdk/services/financing/__init__.py
prime_sdk/services/financing/create_new_locate.py
prime_sdk/services/financing/get_cross_margin_overview.py
prime_sdk/services/financing/get_entity_locate_availabilities.py
prime_sdk/services/financing/get_margin_information.py
prime_sdk/services/financing/get_portfolio_buying_power.py
prime_sdk_py-1.4.0.dist-info/licenses/LICENSE
prime_sdk_py-1.4.0.dist-info/METADATA
prime_sdk_py-1.4.0.dist-info/WHEEL
prime_sdk_py-1.4.0.dist-info/entry_points.txt
prime_sdk_py-1.4.0.dist-info/top_level.txt
prime_sdk_py-1.4.0.dist-info/RECORD
