Metadata-Version: 2.4
Name: prime-sdk-py
Version: 1.4.0
License-File: LICENSE
Requires-Dist: requests
Dynamic: license-file
Dynamic: requires-dist
